pgsql2osm/__init__.py
pgsql2osm/cli.py
pgsql2osm/dbutils.py
pgsql2osm/log.py
pgsql2osm/pgsql2osm.py
pgsql2osm/regions.csv
pgsql2osm/settings.py
pgsql2osm-1.0.1.dist-info/LICENSE
pgsql2osm-1.0.1.dist-info/METADATA
pgsql2osm-1.0.1.dist-info/WHEEL
pgsql2osm-1.0.1.dist-info/entry_points.txt
pgsql2osm-1.0.1.dist-info/top_level.txt
pgsql2osm-1.0.1.dist-info/RECORD
