Metadata-Version: 2.1
Name: pgsql2osm
Version: 1.0.1
Project-URL: Homepage, https://github.com/feludwig/pgsql2osm
Project-URL: Issues, https://github.com/feludwig/pgsql2osm/issues
License-File: LICENSE
Requires-Dist: lxml
Requires-Dist: psycopg2-binary
